honeycomb/__danger.py
honeycomb/__init__.py
honeycomb/_version.py
honeycomb/alter_table.py
honeycomb/analysis.py
honeycomb/append_table.py
honeycomb/config.py
honeycomb/connection.py
honeycomb/ddl_building.py
honeycomb/describe_table.py
honeycomb/dtype_mapping.py
honeycomb/hive.py
honeycomb/inform.py
honeycomb/meta.py
honeycomb/orc.py
honeycomb/check/__init__.py
honeycomb/check/existence_checks.py
honeycomb/create_table/__init__.py
honeycomb/create_table/build_and_run_ddl_stmt.py
honeycomb/create_table/common.py
honeycomb/create_table/create_table_from_df.py
honeycomb/create_table/ctas.py
honeycomb/create_table/flash_update_table_from_df.py
honeycomb/extras/__init__.py
honeycomb/extras/bigquery.py
honeycomb/extras/get_ssm_secret.py
honeycomb/extras/salesforce.py
honeycomb-1.7.2.dist-info/METADATA
honeycomb-1.7.2.dist-info/WHEEL
honeycomb-1.7.2.dist-info/top_level.txt
honeycomb-1.7.2.dist-info/RECORD
