Metadata-Version: 2.1
Name: honeycomb
Version: 1.7.2
Summary: Multi-source/engine querying tool
Home-page: https://github.com/neighborhoods/honeycomb
Author: George Wood (@Geoiv)
Author-email: george.wood@55places.com
License: UNKNOWN
Platform: UNKNOWN
Requires-Dist: pandas (>=0.25.3)
Requires-Dist: pyhive[hive,presto] (>=0.6.1)
Requires-Dist: rivet (>=1.6)
Requires-Dist: pandavro (>=1.6)
Provides-Extra: bigquery
Requires-Dist: google-auth (>=1.22) ; extra == 'bigquery'
Requires-Dist: pandas-gbq (>=0.14) ; extra == 'bigquery'
Provides-Extra: salesforce
Requires-Dist: simple-salesforce (>=1.1.0) ; extra == 'salesforce'
